air_web-0.1.0.dist-info/METADATA
air_web-0.1.0.dist-info/WHEEL
air_web.libs/libgcc_s-1e52349c.so.1
air_web/core.py
air_web/air_web.pyi
air_web/primp.py
air_web/__init__.py
air_web/primp.pyi
air_web/py.typed
air_web/air_web.cpython-310-x86_64-linux-gnu.so
air_web-0.1.0.dist-info/RECORD
