Metadata-Version: 2.3
Name: air_web
Version: 0.1.0
Classifier: Programming Language :: Rust
Classifier: Programming Language :: Python :: Implementation :: CPython
Classifier: Programming Language :: Python :: Implementation :: PyPy
Requires-Dist: selectolax
Requires-Dist: primp
Requires-Dist: pytest ; extra == 'tests'
Provides-Extra: tests
Summary: A lightweight package for crawling the web with the minimalist of code.
Keywords: web,crawl,markdown,scrape,cralwer,scraper
Author-email: AWeirdDev <aweirdscratcher@gmail.com>
Requires-Python: >=3.8
Project-URL: Homepage, https://github.com/AWeirdDev/air-web
Project-URL: Bug Tracker, https://github.com/AWeirdDev/air-web/issues
